pywinos/__init__.py
pywinos/exceptions.py
pywinos-2.1.0.dist-info/LICENSE
pywinos-2.1.0.dist-info/METADATA
pywinos-2.1.0.dist-info/WHEEL
pywinos-2.1.0.dist-info/top_level.txt
pywinos-2.1.0.dist-info/RECORD
