Metadata-Version: 2.1
Name: pywinos
Version: 2.1.0
Summary: The cross-platform tool to execute PowerShell and commandline commands remotely and locally.
Author-email: Andrey Komissarov <a.komisssarov@gmail.com>
Project-URL: Homepage, https://github.com/c-pher/PyWinOS
Classifier: Programming Language :: Python :: 3
Classifier: License :: OSI Approved :: GNU General Public License v3 (GPLv3)
Classifier: Operating System :: OS Independent
Requires-Python: >=3.10
License-File: LICENSE
Requires-Dist: pywinrm >=0.4.1
Requires-Dist: plogger >=1.0.8
Requires-Dist: requests-credssp >=1.1.1
Requires-Dist: requests >=2.31.0
Requires-Dist: xmltodict
